kayobe/__init__.py
kayobe/ansible.py
kayobe/environment.py
kayobe/exception.py
kayobe/kolla_ansible.py
kayobe/utils.py
kayobe/vault.py
kayobe/version.py
kayobe/cli/__init__.py
kayobe/cli/commands.py
kayobe/cmd/__init__.py
kayobe/cmd/kayobe.py
kayobe/cmd/kayobe_vault_password_helper.py
kayobe/plugins/__init__.py
kayobe/plugins/action/__init__.py
kayobe/plugins/action/kolla_ansible_host_vars.py
kayobe/plugins/action/merge_configs.py
kayobe/plugins/action/merge_yaml.py
kayobe/plugins/action/template_content.py
kayobe/plugins/filter/__init__.py
kayobe/plugins/filter/networkd.py
kayobe/plugins/filter/networks.py
kayobe/plugins/filter/utils.py
kayobe/plugins/lookup/environments.py
kayobe/tests/__init__.py
kayobe/tests/molecule/__init__.py
kayobe/tests/molecule/utils.py
kayobe/tests/unit/__init__.py
kayobe/tests/unit/test_ansible.py
kayobe/tests/unit/test_environment.py
kayobe/tests/unit/test_kolla_ansible.py
kayobe/tests/unit/test_utils.py
kayobe/tests/unit/test_vault.py
kayobe/tests/unit/cli/__init__.py
kayobe/tests/unit/cli/test_commands.py
kayobe/tests/unit/plugins/__init__.py
kayobe/tests/unit/plugins/action/__init__.py
kayobe/tests/unit/plugins/action/test_kolla_ansible_host_vars.py
kayobe/tests/unit/plugins/action/test_merge_config.py
kayobe/tests/unit/plugins/action/test_merge_yaml.py
kayobe/tests/unit/plugins/filter/__init__.py
kayobe/tests/unit/plugins/filter/test_networkd.py
kayobe/tests/unit/plugins/filter/test_networks.py
kayobe-19.0.0.data/data/share/kayobe/requirements.yml
kayobe-19.0.0.data/data/share/kayobe/setup.cfg
kayobe-19.0.0.data/data/share/kayobe/ansible/apparmor-libvirt.yml
kayobe-19.0.0.data/data/share/kayobe/ansible/apt.yml
kayobe-19.0.0.data/data/share/kayobe/ansible/baremetal-compute-inspect.yml
kayobe-19.0.0.data/data/share/kayobe/ansible/baremetal-compute-introspection-data-save.yml
kayobe-19.0.0.data/data/share/kayobe/ansible/baremetal-compute-manage.yml
kayobe-19.0.0.data/data/share/kayobe/ansible/baremetal-compute-provide.yml
kayobe-19.0.0.dist-info/AUTHORS
kayobe-19.0.0.dist-info/LICENSE
kayobe-19.0.0.dist-info/METADATA
kayobe-19.0.0.dist-info/WHEEL
kayobe-19.0.0.dist-info/entry_points.txt
kayobe-19.0.0.dist-info/pbr.json
kayobe-19.0.0.dist-info/top_level.txt
kayobe-19.0.0.dist-info/RECORD
