Metadata-Version: 2.1
Name: kayobe
Version: 19.0.0
Summary: Deployment of OpenStack to bare metal using OpenStack kolla and bifrost
Home-page: https://docs.openstack.org/kayobe/latest/
Author: OpenStack
Author-email: openstack-discuss@lists.openstack.org
License: Apache License, Version 2.0
Classifier: Environment :: OpenStack
Classifier: Intended Audience :: Information Technology
Classifier: Intended Audience :: System Administrators
Classifier: License :: OSI Approved :: Apache Software License
Classifier: Operating System :: POSIX :: Linux
Classifier: Programming Language :: Python
Classifier: Programming Language :: Python :: Implementation :: CPython
Classifier: Programming Language :: Python :: 3 :: Only
Classifier: Programming Language :: Python :: 3
Classifier: Programming Language :: Python :: 3.12
Requires-Python: >=3.12
License-File: LICENSE
License-File: AUTHORS
Requires-Dist: pbr >=2.0
Requires-Dist: Jinja2 >3
Requires-Dist: ansible <13,>=11
Requires-Dist: cliff >=3.1.0
Requires-Dist: netaddr !=0.7.16,>=0.7.13
Requires-Dist: PyYAML >=3.10.0
Requires-Dist: oslo.config >=5.2.0
Requires-Dist: paramiko
Requires-Dist: jsonschema <5
Requires-Dist: wcmatch <=9.0,>=8.2
Requires-Dist: hvac >=0.10.1
Requires-Dist: ansible-cached-lookup <=2.0.0
